AUTHORS
MANIFEST.in
README
TODO
setup.py
chishop/.settings.py.swp
chishop/__init__.py
chishop/__init__.pyc
chishop/devdatabase.db
chishop/development.py
chishop/manage.py
chishop/settings.py
chishop/settings.pyc
chishop/urls.py
chishop/urls.pyc
chishop.egg-info/PKG-INFO
chishop.egg-info/SOURCES.txt
chishop.egg-info/dependency_links.txt
chishop.egg-info/not-zip-safe
chishop.egg-info/requires.txt
chishop.egg-info/top_level.txt
chishop/media/__init__.py
chishop/media/dists/__init__.py
djangopypi/.__init__.py.swp
djangopypi/.forms.py.swp
djangopypi/.urls.py.swp
djangopypi/.views.py.swp
djangopypi/__init__.py
djangopypi/__init__.pyc
djangopypi/admin.py
djangopypi/forms.py
djangopypi/models.py
djangopypi/urls.py
djangopypi/views.py
djangopypi/templates/.show_links.html.swp
djangopypi/templates/djangopypi/.show_links.html.swp
djangopypi/templates/djangopypi/.show_version.html.swp
djangopypi/templates/djangopypi/.simple.html.swp
djangopypi/templates/djangopypi/show_links.html
djangopypi/templates/djangopypi/show_version.html
djangopypi/templates/djangopypi/simple.html