Metadata-Version: 1.0
Name: chishop
Version: 0.2.0
Summary: Simple PyPI server written in Django.
Home-page: http://ask.github.com/chishop
Author: Ask Solem
Author-email: askh@opera.com
License: UNKNOWN
Platform: UNKNOWN
Classifier: Development Status :: 3 - Alpha
Classifier: Environment :: Web Environment
Classifier: Framework :: Django
Classifier: Operating System :: OS Independent
Classifier: Intended Audience :: Developers
Classifier: Intended Audience :: System Administrators
Classifier: License :: OSI Approved :: BSD License
Classifier: Topic :: System :: Software Distribution
Classifier: Programming Language :: Python
